README.md
setup.cfg
setup.py
M_challenge.egg-info/PKG-INFO
M_challenge.egg-info/SOURCES.txt
M_challenge.egg-info/dependency_links.txt
M_challenge.egg-info/top_level.txt
data_etl/__init__.py
data_etl/__main__.py
data_etl/data_grab.py
data_etl/process_csv.py
data_etl/stage_data.py