Metadata-Version: 2.1
Name: M-challenge
Version: 0.0.2
Summary: A tool for extracting data and reading csv into datafames details
Home-page: https://github.com/VBamgbaye/M_Challenge
Author: Victor Bamgbaye
Author-email: bamgbayev@gmail.com
License: MIT
Platform: UNKNOWN
